phovea_server/__init__.py
phovea_server/__main__.py
phovea_server/_plugin_parser.py
phovea_server/_utils.py
phovea_server/apiutil.py
phovea_server/colors.py
phovea_server/config.json
phovea_server/config.py
phovea_server/dataset.py
phovea_server/dataset_api.py
phovea_server/dataset_def.py
phovea_server/dispatcher.py
phovea_server/graph.py
phovea_server/graph_api.py
phovea_server/graph_parser.py
phovea_server/json_encoder.py
phovea_server/launch.py
phovea_server/mainapp.py
phovea_server/mapper.py
phovea_server/ns.py
phovea_server/plugin.py
phovea_server/security.py
phovea_server/server.py
phovea_server/set_encoder.py
phovea_server/util.py
phovea_server/websocket.py
phovea_server/wsgi.py
phovea_server-10.0.0.dist-info/LICENSE
phovea_server-10.0.0.dist-info/METADATA
phovea_server-10.0.0.dist-info/WHEEL
phovea_server-10.0.0.dist-info/entry_points.txt
phovea_server-10.0.0.dist-info/top_level.txt
phovea_server-10.0.0.dist-info/RECORD
