Metadata-Version: 2.1
Name: phovea-server
Version: 10.0.0
Summary: DEPRECATED: Python server implementation of Phovea
Home-page: https://phovea.caleydo.org
Author: The Caleydo Team
Author-email: contact@caleydo.org
License: BSD-3-Clause
Platform: UNKNOWN
Classifier: Intended Audience :: Developers
Classifier: Operating System :: OS Independent
Classifier: License :: OSI Approved :: BSD License
Classifier: Programming Language :: Python
Classifier: Programming Language :: Python :: 3.7
License-File: LICENSE
Requires-Dist: Flask (==1.1.4)
Requires-Dist: flask-restplus (==0.13.0)
Requires-Dist: Flask-Sockets (==0.2.1)
Requires-Dist: gevent (==20.9.0)
Requires-Dist: gevent-websocket (==0.10.1)
Requires-Dist: numpy (==1.19.4)
Requires-Dist: scipy (==1.5.4)
Requires-Dist: pandas (==1.1.4)
Requires-Dist: matplotlib (==3.3.3)
Requires-Dist: Pillow (==8.3.2)
Requires-Dist: json-cfg (==0.4.2)
Requires-Dist: docutils (==0.17.1)
Requires-Dist: markupsafe (==2.0.1)
